{
  "kind": "collectionType",
  "collectionName": "products",
  "info": {
    "singularName": "product",
    "pluralName": "products",
    "displayName": "Product",
    "description": ""
  },
  "options": {
    "draftAndPublish": true
  },
  "pluginOptions": {
    "i18n": {
      "localized": true
    }
  },
  "attributes": {
    "title": {
      "pluginOptions": {
        "i18n": {
          "localized": true
        }
      },
      "type": "string",
      "required": true
    },
    "subtitle": {
      "pluginOptions": {
        "i18n": {
          "localized": true
        }
      },
      "type": "string"
    },
    "short_description": {
      "pluginOptions": {
        "i18n": {
          "localized": true
        }
      },
      "type": "text"
    },
    "medias": {
      "type": "media",
      "multiple": true,
      "required": true,
      "allowedTypes": [
        "images",
        "videos"
      ],
      "pluginOptions": {
        "i18n": {
          "localized": true
        }
      }
    },
    "content_classifications": {
      "type": "relation",
      "relation": "manyToMany",
      "target": "api::content-classification.content-classification",
      "inversedBy": "products"
    },
    "category_groups": {
      "type": "relation",
      "relation": "manyToMany",
      "target": "api::category-group.category-group",
      "inversedBy": "products"
    },
    "category": {
      "type": "relation",
      "relation": "manyToOne",
      "target": "api::category.category",
      "inversedBy": "products"
    }
  }
}
